incenp/__init__.py
incenp/__pycache__/__init__.cpython-39.pyc
incenp/grainyhead/__init__.py
incenp/grainyhead/caching.py
incenp/grainyhead/filtering.py
incenp/grainyhead/main.py
incenp/grainyhead/metrics.py
incenp/grainyhead/providers.py
incenp/grainyhead/repository.py
incenp/grainyhead/util.py
incenp/grainyhead/__pycache__/__init__.cpython-39.pyc
incenp/grainyhead/__pycache__/providers.cpython-39.pyc
grainyhead-0.3.2.dist-info/AUTHORS
grainyhead-0.3.2.dist-info/COPYING
grainyhead-0.3.2.dist-info/METADATA
grainyhead-0.3.2.dist-info/WHEEL
grainyhead-0.3.2.dist-info/entry_points.txt
grainyhead-0.3.2.dist-info/top_level.txt
grainyhead-0.3.2.dist-info/RECORD
