Metadata-Version: 2.1
Name: grainyhead
Version: 0.3.2
Summary: Helper tools for GitHub
Home-page: UNKNOWN
Author: Damien Goutte-Gattat
Author-email: dpg44@cam.ac.uk
License: UNKNOWN
Platform: UNKNOWN
Classifier: Development Status :: 1 - Planning
Classifier: Environment :: Console
Classifier: License :: OSI Approved :: GNU General Public License v3 or later (GPLv3+)
Classifier: Programming Language :: Python :: 3.9
Classifier: Intended Audience :: Developers
License-File: COPYING
License-File: AUTHORS
Requires-Dist: click-shell (>=2.1)
Requires-Dist: ghapi
Requires-Dist: python-dateutil
Requires-Dist: pyparsing (>=3.0.0)
Provides-Extra: ipython
Requires-Dist: ipython ; extra == 'ipython'
